tkextrafont-0.6.3.dist-info/top_level.txt
tkextrafont-0.6.3.dist-info/WHEEL
tkextrafont-0.6.3.dist-info/METADATA
tkextrafont-0.6.3.dist-info/RECORD
tkextrafont-0.6.3.dist-info/LICENSE.md
tkextrafont.libs/libbz2-a273e504.so.1.0.6
tkextrafont.libs/libuuid-f64cda11.so.1.3.0
tkextrafont.libs/libfontconfig-42c558d2.so.1.11.1
tkextrafont.libs/libpng15-ce838cd1.so.15.13.0
tkextrafont.libs/libz-745e0a09.so.1.2.7
tkextrafont.libs/libfreetype-c0e61f0c.so.6.14.0
tkextrafont/libextrafont.so
tkextrafont/fontnameinfo.tcl
tkextrafont/__init__.py
tkextrafont/futmp.tcl
tkextrafont/extrafont.tcl
tkextrafont/pkgIndex.tcl
