Metadata-Version: 2.1
Name: tkextrafont
Version: 0.6.3
Summary: Fonts loader for Tkinter
Home-page: https://github.com/TkinterEP/tkextrafont
Author: The extrafont and tkextrafont authors
License: GNU GPLv3
Download-URL: https://github.com/TkinterEP/tkextrafont/releases
Platform: UNKNOWN
License-File: LICENSE.md
Requires-Dist: scikit-build
